{
  "version": "6",
  "dialect": "sqlite",
  "id": "fbd2c5cc-74bd-467f-b8cb-5d4df21ff95b",
  "prevId": "00000000-0000-0000-0000-000000000000",
  "tables": {
    "participants": {
      "name": "participants",
      "columns": {
        "id": {
          "name": "id",
          "type": "integer",
          "primaryKey": true,
          "notNull": true,
          "autoincrement": true
        },
        "session_id": {
          "name": "session_id",
          "type": "integer",
          "primaryKey": false,
          "notNull": true,
          "autoincrement": false
        },
        "name": {
          "name": "name",
          "type": "text",
          "primaryKey": false,
          "notNull": true,
          "autoincrement": false
        },
        "base_name": {
          "name": "base_name",
          "type": "text",
          "primaryKey": false,
          "notNull": true,
          "autoincrement": false
        },
        "created_at": {
          "name": "created_at",
          "type": "integer",
          "primaryKey": false,
          "notNull": true,
          "autoincrement": false,
          "default": "(unixepoch() * 1000)"
        }
      },
      "indexes": {
        "participants_session_idx": {
          "name": "participants_session_idx",
          "columns": [
            "session_id",
            "id"
          ],
          "isUnique": false
        }
      },
      "foreignKeys": {
        "participants_session_id_sessions_id_fk": {
          "name": "participants_session_id_sessions_id_fk",
          "tableFrom": "participants",
          "tableTo": "sessions",
          "columnsFrom": [
            "session_id"
          ],
          "columnsTo": [
            "id"
          ],
          "onDelete": "cascade",
          "onUpdate": "no action"
        }
      },
      "compositePrimaryKeys": {},
      "uniqueConstraints": {},
      "checkConstraints": {}
    },
    "sessions": {
      "name": "sessions",
      "columns": {
        "id": {
          "name": "id",
          "type": "integer",
          "primaryKey": true,
          "notNull": true,
          "autoincrement": true
        },
        "source_id": {
          "name": "source_id",
          "type": "text",
          "primaryKey": false,
          "notNull": true,
          "autoincrement": false
        },
        "header": {
          "name": "header",
          "type": "text",
          "primaryKey": false,
          "notNull": true,
          "autoincrement": false
        },
        "created_at": {
          "name": "created_at",
          "type": "integer",
          "primaryKey": false,
          "notNull": true,
          "autoincrement": false,
          "default": "(unixepoch() * 1000)"
        }
      },
      "indexes": {
        "sessions_source_idx": {
          "name": "sessions_source_idx",
          "columns": [
            "source_id",
            "id"
          ],
          "isUnique": false
        }
      },
      "foreignKeys": {},
      "compositePrimaryKeys": {},
      "uniqueConstraints": {},
      "checkConstraints": {}
    }
  },
  "views": {},
  "enums": {},
  "_meta": {
    "schemas": {},
    "tables": {},
    "columns": {}
  },
  "internal": {
    "indexes": {}
  }
}